setup.py
watson_speech_to_text_websockets/__init__.py
watson_speech_to_text_websockets/ws_speech_to_text_v1.py
watson_speech_to_text_websockets.egg-info/PKG-INFO
watson_speech_to_text_websockets.egg-info/SOURCES.txt
watson_speech_to_text_websockets.egg-info/dependency_links.txt
watson_speech_to_text_websockets.egg-info/requires.txt
watson_speech_to_text_websockets.egg-info/top_level.txt