Metadata-Version: 1.1
Name: watson-speech-to-text-websockets
Version: 0.1.0
Summary: A subclass of the Watson Developer Cloud Speech to Text class that supports websockets
Home-page: https://github.com/kognate/watson_speech_to_text_websockets
Author: Joshua B. Smith
Author-email: kognate@gmail.com
License: MIT
Platform: UNKNOWN
Classifier: Programming Language :: Python
Classifier: Programming Language :: Python :: 3.5
